src/__init__.py
src/raw_database/__init__.py
src/raw_database/base.py
src/raw_database/action/__init__.py
src/raw_database/action/insert.py
src/raw_database/action/queryset.py
src/raw_database/action/update.py
tests/__init__.py
tests/test.py
raw_databases-0.0.1.dist-info/METADATA
raw_databases-0.0.1.dist-info/WHEEL
raw_databases-0.0.1.dist-info/top_level.txt
raw_databases-0.0.1.dist-info/RECORD
