Metadata-Version: 2.1
Name: raw-databases
Version: 0.0.1
Summary: Simple Module Using Raw SQL To Get Insert Update Database
Author: TriNguyen
Author-email: <trinct1412@gmail.com>
Keywords: python,database,raw database,postgrest,mysql
Classifier: Programming Language :: Python :: 3
Classifier: License :: OSI Approved :: PostgreSQL License
Classifier: Operating System :: MacOS :: MacOS X
Requires-Dist: SQLAlchemy
